[
  {
    "name": "wa",
    "color": "#d51010",
    "description": "",
    "lead": "wadwawadawdaw",
    "follow": "wa",
    "both": "wa",
    "link": ""
  },
  {
    "name": "Chasse",
    "color": "#400707",
    "description": "asdddddddasdasdasd",
    "lead": "asdddddddasdasdasd",
    "follow": "wa",
    "both": "wa",
    "link": ""
  },
  {
    "name": "wawad",
    "color": "#7dd3fc",
    "description": "",
    "lead": "",
    "follow": "",
    "both": "",
    "link": ""
  },
  {
    "name": "waddwadw",
    "color": "#7dd3fc",
    "description": "",
    "lead": "",
    "follow": "",
    "both": "",
    "link": ""
  },
  {
    "name": "12",
    "color": "#7dd3fc",
    "description": "aaaaaaaaaaaaaaaaaaaaaaaaa",
    "lead": "aaaaaaaaaaaaaaaaaaaaaaaaa",
    "follow": "",
    "both": "",
    "link": ""
  },
  {
    "name": "saasas",
    "color": "#7dd3fc",
    "description": "",
    "lead": "",
    "follow": "",
    "both": "",
    "link": ""
  },
  {
    "name": "ssas",
    "color": "#7dd3fc",
    "description": "",
    "lead": "",
    "follow": "",
    "both": "",
    "link": ""
  },
  {
    "name": "asassa",
    "color": "#7dd3fc",
    "description": "dasdasdadasd",
    "lead": "dasdasdadasd",
    "follow": "",
    "both": "",
    "link": ""
  },
  {
    "name": "asasas",
    "color": "#7dd3fc",
    "description": "",
    "lead": "",
    "follow": "",
    "both": "",
    "link": ""
  },
  {
    "name": "1111111111111111111111",
    "color": "#7dd3fc",
    "description": "",
    "lead": "",
    "follow": "dsadasdasdad",
    "both": "",
    "link": ""
  },
  {
    "name": "1212",
    "color": "#7dd3fc",
    "description": "",
    "lead": "",
    "follow": "",
    "both": "",
    "link": ""
  },
  {
    "name": "proba",
    "color": "#7dd3fc",
    "description": "dasdasd",
    "lead": "dasdasd",
    "follow": "dasdasd",
    "both": "asddas",
    "link": "https://www.youtube.com/watch?v=J2c4-vYPzpU"
  }
]